hanmatek/HM3xxP.py
hanmatek/HM3xxP_regmap.py
hanmatek/__init__.py
hanmatek/__main__.py
hanmatek/py.typed
hanmatek_psu-1.1.2.dist-info/LICENSE
hanmatek_psu-1.1.2.dist-info/METADATA
hanmatek_psu-1.1.2.dist-info/WHEEL
hanmatek_psu-1.1.2.dist-info/entry_points.txt
hanmatek_psu-1.1.2.dist-info/RECORD
