Metadata-Version: 2.1
Name: hanmatek-psu
Version: 1.1.2
Summary: Library and CLI for the Hanmatek Power supply units (PSU) of the HM3xxP series.
Home-page: https://gitlab.com/janoskut/hanmatek-psu/-/tree/main
License: MIT
Keywords: power-supply,psu,equipment,lab,automation
Author: Janos
Author-email: janoskut@gmail.com
Maintainer: Janos
Maintainer-email: janoskut@gmail.com
Requires-Python: >=3.8
Classifier: Intended Audience :: Developers
Classifier: Intended Audience :: Science/Research
Classifier: License :: OSI Approved :: MIT License
Classifier: Operating System :: Unix
Classifier: Programming Language :: Python :: 3
Classifier: Programming Language :: Python :: 3.8
Classifier: Programming Language :: Python :: 3.9
Classifier: Programming Language :: Python :: 3.10
Classifier: Programming Language :: Python :: 3.11
Classifier: Topic :: Software Development :: Embedded Systems
Classifier: Topic :: Software Development :: Testing
Classifier: Topic :: System :: Hardware :: Hardware Drivers
Requires-Dist: minimalmodbus (>=2.0.1,<3.0.0)
Project-URL: Repository, https://gitlab.com/janoskut/hanmatek-psu/-/tree/main
